web_plotter/__init__.py
web_plotter/fuzzy.py
web_plotter/helper.py
web_plotter/plot.py
web_plotter/static/css/fuzzy_finder.css
web_plotter/static/css/grid_plotter.css
web_plotter/static/js/fuzzy_finder.js
web_plotter/static/js/grid_plotter.js
web_plotter/templates/chartjs_example.html
web_plotter/templates/file_reader_example.html
web_plotter/templates/fuzzy_finder.html
web_plotter/templates/grid_plotter.html
web_plotter-0.0.1.dist-info/LICENSE
web_plotter-0.0.1.dist-info/METADATA
web_plotter-0.0.1.dist-info/WHEEL
web_plotter-0.0.1.dist-info/top_level.txt
web_plotter-0.0.1.dist-info/zip-safe
web_plotter-0.0.1.dist-info/RECORD
